pivtestdata/__init__.py
pivtestdata/_version.py
pivtestdata/image.py
pivtestdata/piv_challenge.py
pivtestdata/pivtec.py
pivtestdata/webzip.py
pivtestdata-0.5.0.dist-info/LICENSE
pivtestdata-0.5.0.dist-info/METADATA
pivtestdata-0.5.0.dist-info/WHEEL
pivtestdata-0.5.0.dist-info/top_level.txt
pivtestdata-0.5.0.dist-info/RECORD
