Metadata-Version: 2.1
Name: pivtestdata
Version: 0.5.0
Summary: Repository providing PIV test data
Home-page: https://github.com/matthiasprobst/piv-test-data
Author: Matthias Probst
Author-email: matthias.probst@kit.edu
Classifier: Programming Language :: Python :: 3
Classifier: Programming Language :: Python :: 3.8
Classifier: Programming Language :: Python :: 3.9
Classifier: Programming Language :: Python :: 3.10
Classifier: Programming Language :: Python :: 3.11
Classifier: Programming Language :: Python :: 3.12
Classifier: Programming Language :: Python :: 3.13
Classifier: License :: OSI Approved :: MIT License
Classifier: Operating System :: OS Independent
Classifier: Development Status :: 4 - Beta
Requires-Python: >=3.8
License-File: LICENSE
Requires-Dist: appdirs>=1.4.4
Requires-Dist: requests
Requires-Dist: tqdm
Requires-Dist: opencv-python>=4.5.3.56
Requires-Dist: pco-tools>=1.0.0
Requires-Dist: numpy
Requires-Dist: matplotlib
Provides-Extra: test
Requires-Dist: numpy; extra == "test"
Requires-Dist: pytest; extra == "test"
Requires-Dist: pytest-cov; extra == "test"
